setup.py
test/__init__.py
test/billboard_test.py
test/classifying_test.py
test/dateu_test.py
test/fund_test.py
test/macro_test.py
test/nav_test.py
test/news_test.py
test/ref_test.py
test/shibor_test.py
test/storing_test.py
test/trading_test.py
tusharec/__init__.py
tusharec.egg-info/PKG-INFO
tusharec.egg-info/SOURCES.txt
tusharec.egg-info/dependency_links.txt
tusharec.egg-info/top_level.txt
tusharec/data/__init__.py
tusharec/datayes/HKequity.py
tusharec/datayes/IV.py
tusharec/datayes/__init__.py
tusharec/datayes/api.py
tusharec/datayes/bond.py
tusharec/datayes/equity.py
tusharec/datayes/fund.py
tusharec/datayes/fundamental.py
tusharec/datayes/future.py
tusharec/datayes/idx.py
tusharec/datayes/macro.py
tusharec/datayes/market.py
tusharec/datayes/master.py
tusharec/datayes/options.py
tusharec/datayes/subject.py
tusharec/fund/__init__.py
tusharec/fund/cons.py
tusharec/fund/nav.py
tusharec/futures/__init__.py
tusharec/futures/cons.py
tusharec/futures/intlfutures.py
tusharec/internet/__init__.py
tusharec/internet/boxoffice.py
tusharec/stock/__init__.py
tusharec/stock/billboard.py
tusharec/stock/classifying.py
tusharec/stock/cons.py
tusharec/stock/fundamental.py
tusharec/stock/globals.py
tusharec/stock/macro.py
tusharec/stock/macro_vars.py
tusharec/stock/news_vars.py
tusharec/stock/newsevent.py
tusharec/stock/ref_vars.py
tusharec/stock/reference.py
tusharec/stock/shibor.py
tusharec/stock/trading.py
tusharec/trader/__init__.py
tusharec/trader/trader.py
tusharec/trader/utils.py
tusharec/trader/vars.py
tusharec/util/__init__.py
tusharec/util/common.py
tusharec/util/dateu.py
tusharec/util/netbase.py
tusharec/util/store.py
tusharec/util/upass.py
tusharec/util/vars.py